metaperceptron/__init__.py
metaperceptron/core/__init__.py
metaperceptron/core/base_mlp.py
metaperceptron/core/comparator.py
metaperceptron/core/gradient_mlp.py
metaperceptron/core/metaheuristic_mlp.py
metaperceptron/core/tuner.py
metaperceptron/helpers/__init__.py
metaperceptron/helpers/metric_util.py
metaperceptron/helpers/preprocessor.py
metaperceptron/helpers/scaler_util.py
metaperceptron/helpers/validator.py
metaperceptron-2.2.0.dist-info/licenses/LICENSE
metaperceptron-2.2.0.dist-info/METADATA
metaperceptron-2.2.0.dist-info/WHEEL
metaperceptron-2.2.0.dist-info/top_level.txt
metaperceptron-2.2.0.dist-info/RECORD
